{"chunk_definitions":[{"row":71,"row_count":1,"visible":true,"expansion_state":0,"options":{"engine":"r","label":"Caesar Cipher","echo":true},"document_id":"689A2DB6","chunk_id":"c7okzit8jodnn","chunk_label":"Caesar Cipher"},{"row":87,"row_count":1,"visible":true,"expansion_state":0,"options":{"engine":"r","label":"Sub Cipher","echo":true},"document_id":"689A2DB6","chunk_id":"ci4rgxqdlb57o","chunk_label":"unnamed-chunk-1"},{"row":155,"row_count":1,"visible":true,"expansion_state":0,"options":{"engine":"r","include":false,"label":"unnamed-chunk-23"},"document_id":"689A2DB6","chunk_id":"ck5j5rxtmrvqe","chunk_label":"unnamed-chunk-2"}],"doc_write_time":1694045601}